topsis/__init__.py
Topsis_akhil_101917103-1.0.0.dist-info/LICENSE
Topsis_akhil_101917103-1.0.0.dist-info/METADATA
Topsis_akhil_101917103-1.0.0.dist-info/WHEEL
Topsis_akhil_101917103-1.0.0.dist-info/top_level.txt
Topsis_akhil_101917103-1.0.0.dist-info/RECORD
